cashfree/__init__.py
cashfree/main.py
cashfree-1.0.1.dist-info/METADATA
cashfree-1.0.1.dist-info/WHEEL
cashfree-1.0.1.dist-info/top_level.txt
cashfree-1.0.1.dist-info/RECORD
