Metadata-Version: 2.1
Name: cashfree
Version: 1.0.1
Summary: A Python library for interacting with CashFree API.
Home-page: https://github.com/devbijay/cashfree
Author: Bijay Nayak
Author-email: bijay6779@gmail.com
License: MIT
Keywords: cashfree payment-api cashfree-api
Classifier: Development Status :: 5 - Production/Stable
Classifier: Intended Audience :: Developers
Classifier: Programming Language :: Python :: 3
Classifier: Operating System :: Unix
Classifier: Operating System :: MacOS :: MacOS X
Classifier: Operating System :: Microsoft :: Windows
Requires-Python: >=3.6
Requires-Dist: requests
Requires-Dist: pydantic
